MANIFEST.in
README.rst
setup.py
src/dj/__init__.py
src/dj.egg-info/PKG-INFO
src/dj.egg-info/SOURCES.txt
src/dj.egg-info/dependency_links.txt
src/dj.egg-info/namespace_packages.txt
src/dj.egg-info/not-zip-safe
src/dj.egg-info/requires.txt
src/dj.egg-info/top_level.txt