Metadata-Version: 1.1
Name: dj
Version: 0.1
Summary: This is a namespace package for extra Django packages. Feel free to use it.
Home-page: https://github.com/ambv/dj/
Author: Łukasz Langa
Author-email: lukasz@langa.pl
License: MIT
Keywords: django dj extra contrib
Platform: any
Classifier: Development Status :: 5 - Production/Stable
Classifier: Framework :: Django
Classifier: License :: OSI Approved :: MIT License
Classifier: Natural Language :: English
Classifier: Programming Language :: Python
Classifier: Programming Language :: Python :: 2
Classifier: Programming Language :: Python :: 3
Classifier: Topic :: Internet :: WWW/HTTP
Classifier: Topic :: Software Development :: Libraries :: Python Modules
